lektor_citation.py
lektor_citation-0.21.dist-info/LICENSE
lektor_citation-0.21.dist-info/METADATA
lektor_citation-0.21.dist-info/WHEEL
lektor_citation-0.21.dist-info/entry_points.txt
lektor_citation-0.21.dist-info/top_level.txt
lektor_citation-0.21.dist-info/RECORD
