Metadata-Version: 2.1
Name: lektor-citation
Version: 0.21
Summary: This Plugin should extend lektor with APA-styled citations using bibtex files. It was based on the known lektor-bibtex-support plugin by arunpersaud.
Home-page: https://git.ismus.net/homer77/lektor-citation
Author: Homer S
Author-email: homer77@ismus.net
License: MIT
Keywords: Lektor plugin
Platform: UNKNOWN
Classifier: Framework :: Lektor
Classifier: Environment :: Plugins
License-File: LICENSE
Requires-Dist: pybtex
Requires-Dist: pylatexenc
Requires-Dist: lektor-jinja-content
